Metadata-Version: 1.0
Name: hopslugprefixlib
Version: 1.0
Summary: Generate "slug" and parent prefixes
Home-page: https://pyug.at
Author: Thomas Perl
Author-email: m@thp.io
License: UNKNOWN
Platform: UNKNOWN
